pptestgosiaprzybysz/__init__.py
pptestgosiaprzybysz/m_mod_pptest.py
pptestgosiaprzybysz-0.0.1.dist-info/LICENSE.txt
pptestgosiaprzybysz-0.0.1.dist-info/METADATA
pptestgosiaprzybysz-0.0.1.dist-info/WHEEL
pptestgosiaprzybysz-0.0.1.dist-info/top_level.txt
pptestgosiaprzybysz-0.0.1.dist-info/RECORD
